{
  "request": {
    "method": "POST",
    "url": "/purchase-orders",
    "headers": {
      "Authorization": "Bearer <REDACTED>"
    },
    "body": {
      "vendorId": "2bad9f20-b33f-43ba-a1af-3de477fb4caa",
      "locationId": "loc-capture",
      "notes": "Captured PO",
      "items": [
        {
          "variantId": "v-cap",
          "sku": "CAP-1",
          "title": "Capture Item",
          "qty": 10,
          "unitCost": 5
        }
      ]
    }
  },
  "response": {
    "status": 201,
    "ok": true,
    "error": null,
    "body": {
      "id": "8601b8b2-3951-4f2b-9453-31ff154193fb",
      "poNumber": "PO-2026-00017",
      "vendorId": "2bad9f20-b33f-43ba-a1af-3de477fb4caa",
      "locationId": "loc-capture",
      "status": "DRAFT",
      "subtotal": "50",
      "tax": "0",
      "shipping": "0",
      "total": "50",
      "currency": "USD",
      "expectedAt": null,
      "notes": "Captured PO",
      "createdBy": "822d845a-6092-43b6-81c8-906023fa03ef",
      "approvedBy": null,
      "approvedAt": null,
      "createdAt": "2026-06-10T13:43:39.476Z",
      "updatedAt": "2026-06-10T13:43:39.476Z",
      "items": [
        {
          "id": "25da8aa1-49c3-4342-9f1c-80a09f06b28a",
          "poId": "8601b8b2-3951-4f2b-9453-31ff154193fb",
          "variantId": "v-cap",
          "sku": "CAP-1",
          "title": "Capture Item",
          "orderedQty": 10,
          "receivedQty": 0,
          "unitCost": "5",
          "lineTotal": "50"
        }
      ],
      "vendor": {
        "id": "2bad9f20-b33f-43ba-a1af-3de477fb4caa",
        "name": "Capture Vendor",
        "contactName": null,
        "email": "capture@v.com",
        "phone": null,
        "address": null,
        "taxNumber": null,
        "paymentTerms": "NET-45",
        "isActive": true
      }
    }
  },
  "capturedAt": "2026-06-10T13:43:39Z"
}