{
  "request": {
    "method": "PATCH",
    "url": "/purchase-orders/a0f631ea-dc60-4e42-8a9e-c2a73e7840ea/submit",
    "headers": {
      "Authorization": "Bearer <REDACTED>"
    },
    "body": null
  },
  "response": {
    "status": 200,
    "ok": true,
    "error": null,
    "body": {
      "id": "a0f631ea-dc60-4e42-8a9e-c2a73e7840ea",
      "poNumber": "PO-2026-00010",
      "vendorId": "4141dd3b-1b94-4b0c-b265-7e5f3f58a6e7",
      "locationId": "loc-capture",
      "status": "PENDING_APPROVAL",
      "subtotal": "50",
      "tax": "0",
      "shipping": "0",
      "total": "50",
      "currency": "USD",
      "expectedAt": null,
      "notes": "Captured PO",
      "createdBy": "822d845a-6092-43b6-81c8-906023fa03ef",
      "approvedBy": null,
      "approvedAt": null,
      "createdAt": "2026-06-10T07:02:56.376Z",
      "updatedAt": "2026-06-10T07:02:56.390Z"
    }
  },
  "capturedAt": "2026-06-10T07:02:56Z"
}