{
  "request": {
    "method": "POST",
    "url": "/products",
    "headers": {
      "Authorization": "Bearer <REDACTED>"
    },
    "body": {
      "title": "API Capture Test",
      "status": "DRAFT",
      "vendor": "Capture"
    }
  },
  "response": {
    "status": 201,
    "ok": true,
    "error": null,
    "body": {
      "id": "gid://shopify/Product/10293332836653",
      "legacyResourceId": "10293332836653",
      "title": "API Capture Test",
      "handle": "api-capture-test",
      "status": "DRAFT"
    }
  },
  "capturedAt": "2026-06-11T06:19:21Z"
}