{
  "request": {
    "method": "PATCH",
    "url": "/products/gid%3A%2F%2Fshopify%2FProduct%2F10293327233325",
    "headers": {
      "Authorization": "Bearer <REDACTED>"
    },
    "body": {
      "tags": [
        "captured"
      ]
    }
  },
  "response": {
    "status": 200,
    "ok": true,
    "error": null,
    "body": {
      "id": "gid://shopify/Product/10293327233325",
      "legacyResourceId": "10293327233325",
      "title": "API Capture Test",
      "handle": "api-capture-test",
      "status": "DRAFT"
    }
  },
  "capturedAt": "2026-06-11T05:53:39Z"
}