{
  "request": {
    "method": "GET",
    "url": "/storefront/blogs?first=10",
    "headers": {},
    "body": null
  },
  "response": {
    "status": 200,
    "ok": true,
    "error": null,
    "body": {
      "pageInfo": {
        "hasNextPage": false,
        "endCursor": "eyJsYXN0X2lkIjoxMTgzODI4ODcyMTMsImxhc3RfdmFsdWUiOjExODM4Mjg4NzIxMywib2Zmc2V0IjowfQ=="
      },
      "edges": [
        {
          "cursor": "eyJsYXN0X2lkIjoxMTgzODI4ODcyMTMsImxhc3RfdmFsdWUiOjExODM4Mjg4NzIxMywib2Zmc2V0IjowfQ==",
          "node": {
            "id": "gid://shopify/Blog/118382887213",
            "title": "News",
            "handle": "news"
          }
        }
      ]
    }
  },
  "capturedAt": "2026-06-11T05:54:11Z"
}